{
  "ciphertext_length": 97,
  "analysis": {
    "periodicity": {
      "best_periods": [
        {
          "period": 2,
          "variance": 9.29664870027088e-06
        },
        {
          "period": 3,
          "variance": 2.2638188121334624e-05
        },
        {
          "period": 5,
          "variance": 3.2171637725309064e-05
        }
      ],
      "full_results": {
        "2": {
          "variance": 9.29664870027088e-06,
          "mean_entropy": -0.05511068160257301,
          "groups": [
            {
              "size": 49,
              "unique": 24,
              "entropy": -0.05206164098292379,
              "top_chars": [
                [
                  "W",
                  5
                ],
                [
                  "O",
                  3
                ],
                [
                  "K",
                  3
                ]
              ]
            },
            {
              "size": 48,
              "unique": 21,
              "entropy": -0.058159722222222224,
              "top_chars": [
                [
                  "K",
                  5
                ],
                [
                  "S",
                  4
                ],
                [
                  "F",
                  4
                ]
              ]
            }
          ]
        },
        "3": {
          "variance": 2.2638188121334624e-05,
          "mean_entropy": -0.059687189126109576,
          "groups": [
            {
              "size": 33,
              "unique": 20,
              "entropy": -0.05601469237832873,
              "top_chars": [
                [
                  "S",
                  3
                ],
                [
                  "R",
                  2
                ],
                [
                  "B",
                  2
                ]
              ]
            },
            {
              "size": 32,
              "unique": 21,
              "entropy": -0.056640625,
              "top_chars": [
                [
                  "U",
                  3
                ],
                [
                  "K",
                  3
                ],
                [
                  "B",
                  2
                ]
              ]
            },
            {
              "size": 32,
              "unique": 19,
              "entropy": -0.06640625,
              "top_chars": [
                [
                  "T",
                  4
                ],
                [
                  "K",
                  3
                ],
                [
                  "Q",
                  3
                ]
              ]
            }
          ]
        },
        "4": {
          "variance": 6.147833333333315e-05,
          "mean_entropy": -0.07275555555555555,
          "groups": [
            {
              "size": 25,
              "unique": 18,
              "entropy": -0.0688,
              "top_chars": [
                [
                  "I",
                  3
                ],
                [
                  "W",
                  3
                ],
                [
                  "R",
                  2
                ]
              ]
            },
            {
              "size": 24,
              "unique": 16,
              "entropy": -0.0833333333333333,
              "top_chars": [
                [
                  "K",
                  4
                ],
                [
                  "F",
                  3
                ],
                [
                  "S",
                  2
                ]
              ]
            },
            {
              "size": 24,
              "unique": 15,
              "entropy": -0.07638888888888888,
              "top_chars": [
                [
                  "Z",
                  3
                ],
                [
                  "K",
                  2
                ],
                [
                  "U",
                  2
                ]
              ]
            },
            {
              "size": 24,
              "unique": 18,
              "entropy": -0.0625,
              "top_chars": [
                [
                  "R",
                  2
                ],
                [
                  "L",
                  2
                ],
                [
                  "T",
                  2
                ]
              ]
            }
          ]
        },
        "5": {
          "variance": 3.2171637725309064e-05,
          "mean_entropy": -0.08873961218836567,
          "groups": [
            {
              "size": 20,
              "unique": 14,
              "entropy": -0.09000000000000002,
              "top_chars": [
                [
                  "G",
                  3
                ],
                [
                  "T",
                  3
                ],
                [
                  "O",
                  2
                ]
              ]
            },
            {
              "size": 20,
              "unique": 14,
              "entropy": -0.08500000000000002,
              "top_chars": [
                [
                  "F",
                  3
                ],
                [
                  "I",
                  2
                ],
                [
                  "Q",
                  2
                ]
              ]
            },
            {
              "size": 19,
              "unique": 13,
              "entropy": -0.09141274238227148,
              "top_chars": [
                [
                  "K",
                  3
                ],
                [
                  "B",
                  2
                ],
                [
                  "P",
                  2
                ]
              ]
            },
            {
              "size": 19,
              "unique": 13,
              "entropy": -0.09695290858725764,
              "top_chars": [
                [
                  "R",
                  3
                ],
                [
                  "S",
                  3
                ],
                [
                  "W",
                  2
                ]
              ]
            },
            {
              "size": 19,
              "unique": 15,
              "entropy": -0.08033240997229918,
              "top_chars": [
                [
                  "U",
                  3
                ],
                [
                  "O",
                  2
                ],
                [
                  "I",
                  2
                ]
              ]
            }
          ]
        },
        "6": {
          "variance": 0.00017261292364516986,
          "mean_entropy": -0.09008704584775086,
          "groups": [
            {
              "size": 17,
              "unique": 14,
              "entropy": -0.07958477508650517,
              "top_chars": [
                [
                  "B",
                  2
                ],
                [
                  "V",
                  2
                ],
                [
                  "W",
                  2
                ]
              ]
            },
            {
              "size": 16,
              "unique": 12,
              "entropy": -0.09375,
              "top_chars": [
                [
                  "B",
                  2
                ],
                [
                  "S",
                  2
                ],
                [
                  "K",
                  2
                ]
              ]
            },
            {
              "size": 16,
              "unique": 10,
              "entropy": -0.1171875,
              "top_chars": [
                [
                  "T",
                  3
                ],
                [
                  "K",
                  2
                ],
                [
                  "W",
                  2
                ]
              ]
            },
            {
              "size": 16,
              "unique": 13,
              "entropy": -0.0859375,
              "top_chars": [
                [
                  "S",
                  2
                ],
                [
                  "K",
                  2
                ],
                [
                  "J",
                  2
                ]
              ]
            },
            {
              "size": 16,
              "unique": 13,
              "entropy": -0.0859375,
              "top_chars": [
                [
                  "U",
                  2
                ],
                [
                  "Z",
                  2
                ],
                [
                  "C",
                  2
                ]
              ]
            },
            {
              "size": 16,
              "unique": 14,
              "entropy": -0.078125,
              "top_chars": [
                [
                  "L",
                  2
                ],
                [
                  "F",
                  2
                ],
                [
                  "O",
                  1
                ]
              ]
            }
          ]
        },
        "7": {
          "variance": 0.0004356800858838137,
          "mean_entropy": -0.11104593993134025,
          "groups": [
            {
              "size": 14,
              "unique": 11,
              "entropy": -0.11224489795918369,
              "top_chars": [
                [
                  "O",
                  3
                ],
                [
                  "I",
                  2
                ],
                [
                  "F",
                  1
                ]
              ]
            },
            {
              "size": 14,
              "unique": 12,
              "entropy": -0.09183673469387757,
              "top_chars": [
                [
                  "G",
                  2
                ],
                [
                  "L",
                  2
                ],
                [
                  "B",
                  1
                ]
              ]
            },
            {
              "size": 14,
              "unique": 11,
              "entropy": -0.11224489795918369,
              "top_chars": [
                [
                  "K",
                  3
                ],
                [
                  "P",
                  2
                ],
                [
                  "H",
                  1
                ]
              ]
            },
            {
              "size": 14,
              "unique": 9,
              "entropy": -0.15306122448979592,
              "top_chars": [
                [
                  "K",
                  4
                ],
                [
                  "U",
                  2
                ],
                [
                  "V",
                  2
                ]
              ]
            },
            {
              "size": 14,
              "unique": 12,
              "entropy": -0.09183673469387757,
              "top_chars": [
                [
                  "L",
                  2
                ],
                [
                  "S",
                  2
                ],
                [
                  "U",
                  1
                ]
              ]
            },
            {
              "size": 14,
              "unique": 12,
              "entropy": -0.09183673469387757,
              "top_chars": [
                [
                  "B",
                  2
                ],
                [
                  "U",
                  2
                ],
                [
                  "O",
                  1
                ]
              ]
            },
            {
              "size": 13,
              "unique": 10,
              "entropy": -0.12426035502958582,
              "top_chars": [
                [
                  "D",
                  3
                ],
                [
                  "W",
                  2
                ],
                [
                  "X",
                  1
                ]
              ]
            }
          ]
        },
        "8": {
          "variance": 0.0003071764187996904,
          "mean_entropy": -0.10658078566732414,
          "groups": [
            {
              "size": 13,
              "unique": 12,
              "entropy": -0.08875739644970417,
              "top_chars": [
                [
                  "I",
                  2
                ],
                [
                  "O",
                  1
                ],
                [
                  "G",
                  1
                ]
              ]
            },
            {
              "size": 12,
              "unique": 10,
              "entropy": -0.11111111111111112,
              "top_chars": [
                [
                  "Q",
                  2
                ],
                [
                  "A",
                  2
                ],
                [
                  "B",
                  1
                ]
              ]
            },
            {
              "size": 12,
              "unique": 11,
              "entropy": -0.09722222222222224,
              "top_chars": [
                [
                  "W",
                  2
                ],
                [
                  "K",
                  1
                ],
                [
                  "U",
                  1
                ]
              ]
            },
            {
              "size": 12,
              "unique": 11,
              "entropy": -0.09722222222222224,
              "top_chars": [
                [
                  "T",
                  2
                ],
                [
                  "R",
                  1
                ],
                [
                  "L",
                  1
                ]
              ]
            },
            {
              "size": 12,
              "unique": 10,
              "entropy": -0.11111111111111112,
              "top_chars": [
                [
                  "W",
                  2
                ],
                [
                  "E",
                  2
                ],
                [
                  "U",
                  1
                ]
              ]
            },
            {
              "size": 12,
              "unique": 9,
              "entropy": -0.1388888888888889,
              "top_chars": [
                [
                  "K",
                  3
                ],
                [
                  "F",
                  2
                ],
                [
                  "O",
                  1
                ]
              ]
            },
            {
              "size": 12,
              "unique": 10,
              "entropy": -0.125,
              "top_chars": [
                [
                  "Z",
                  3
                ],
                [
                  "X",
                  1
                ],
                [
                  "O",
                  1
                ]
              ]
            },
            {
              "size": 12,
              "unique": 12,
              "entropy": -0.08333333333333336,
              "top_chars": [
                [
                  "O",
                  1
                ],
                [
                  "L",
                  1
                ],
                [
                  "R",
                  1
                ]
              ]
            }
          ]
        },
        "9": {
          "variance": 0.0002420181445475713,
          "mean_entropy": -0.11612488521579431,
          "groups": [
            {
              "size": 11,
              "unique": 10,
              "entropy": -0.10743801652892562,
              "top_chars": [
                [
                  "P",
                  2
                ],
                [
                  "O",
                  1
                ],
                [
                  "H",
                  1
                ]
              ]
            },
            {
              "size": 11,
              "unique": 9,
              "entropy": -0.12396694214876033,
              "top_chars": [
                [
                  "B",
                  2
                ],
                [
                  "U",
                  2
                ],
                [
                  "R",
                  1
                ]
              ]
            },
            {
              "size": 11,
              "unique": 10,
              "entropy": -0.10743801652892562,
              "top_chars": [
                [
                  "W",
                  2
                ],
                [
                  "K",
                  1
                ],
                [
                  "L",
                  1
                ]
              ]
            },
            {
              "size": 11,
              "unique": 10,
              "entropy": -0.10743801652892562,
              "top_chars": [
                [
                  "G",
                  2
                ],
                [
                  "R",
                  1
                ],
                [
                  "B",
                  1
                ]
              ]
            },
            {
              "size": 11,
              "unique": 11,
              "entropy": -0.09090909090909091,
              "top_chars": [
                [
                  "U",
                  1
                ],
                [
                  "S",
                  1
                ],
                [
                  "L",
                  1
                ]
              ]
            },
            {
              "size": 11,
              "unique": 8,
              "entropy": -0.14049586776859505,
              "top_chars": [
                [
                  "O",
                  2
                ],
                [
                  "T",
                  2
                ],
                [
                  "K",
                  2
                ]
              ]
            },
            {
              "size": 11,
              "unique": 10,
              "entropy": -0.10743801652892562,
              "top_chars": [
                [
                  "S",
                  2
                ],
                [
                  "X",
                  1
                ],
                [
                  "L",
                  1
                ]
              ]
            },
            {
              "size": 10,
              "unique": 9,
              "entropy": -0.12000000000000005,
              "top_chars": [
                [
                  "O",
                  2
                ],
                [
                  "I",
                  1
                ],
                [
                  "Q",
                  1
                ]
              ]
            },
            {
              "size": 10,
              "unique": 8,
              "entropy": -0.14000000000000004,
              "top_chars": [
                [
                  "F",
                  2
                ],
                [
                  "T",
                  2
                ],
                [
                  "G",
                  1
                ]
              ]
            }
          ]
        },
        "10": {
          "variance": 0.0007618204541990554,
          "mean_entropy": -0.14227160493827162,
          "groups": [
            {
              "size": 10,
              "unique": 9,
              "entropy": -0.12000000000000005,
              "top_chars": [
                [
                  "T",
                  2
                ],
                [
                  "O",
                  1
                ],
                [
                  "U",
                  1
                ]
              ]
            },
            {
              "size": 10,
              "unique": 7,
              "entropy": -0.18000000000000002,
              "top_chars": [
                [
                  "F",
                  3
                ],
                [
                  "J",
                  2
                ],
                [
                  "B",
                  1
                ]
              ]
            },
            {
              "size": 10,
              "unique": 7,
              "entropy": -0.16000000000000006,
              "top_chars": [
                [
                  "K",
                  2
                ],
                [
                  "B",
                  2
                ],
                [
                  "S",
                  2
                ]
              ]
            },
            {
              "size": 10,
              "unique": 6,
              "entropy": -0.20000000000000004,
              "top_chars": [
                [
                  "S",
                  3
                ],
                [
                  "R",
                  2
                ],
                [
                  "K",
                  2
                ]
              ]
            },
            {
              "size": 10,
              "unique": 8,
              "entropy": -0.14000000000000007,
              "top_chars": [
                [
                  "U",
                  2
                ],
                [
                  "O",
                  2
                ],
                [
                  "V",
                  1
                ]
              ]
            },
            {
              "size": 10,
              "unique": 9,
              "entropy": -0.12000000000000002,
              "top_chars": [
                [
                  "G",
                  2
                ],
                [
                  "O",
                  1
                ],
                [
                  "L",
                  1
                ]
              ]
            },
            {
              "size": 10,
              "unique": 9,
              "entropy": -0.12000000000000005,
              "top_chars": [
                [
                  "I",
                  2
                ],
                [
                  "X",
                  1
                ],
                [
                  "Q",
                  1
                ]
              ]
            },
            {
              "size": 9,
              "unique": 8,
              "entropy": -0.13580246913580246,
              "top_chars": [
                [
                  "T",
                  2
                ],
                [
                  "O",
                  1
                ],
                [
                  "F",
                  1
                ]
              ]
            },
            {
              "size": 9,
              "unique": 8,
              "entropy": -0.13580246913580246,
              "top_chars": [
                [
                  "W",
                  2
                ],
                [
                  "G",
                  1
                ],
                [
                  "B",
                  1
                ]
              ]
            },
            {
              "size": 9,
              "unique": 9,
              "entropy": -0.1111111111111111,
              "top_chars": [
                [
                  "H",
                  1
                ],
                [
                  "B",
                  1
                ],
                [
                  "N",
                  1
                ]
              ]
            }
          ]
        },
        "11": {
          "variance": 0.0013870668470778369,
          "mean_entropy": -0.15253226711560045,
          "groups": [
            {
              "size": 9,
              "unique": 8,
              "entropy": -0.13580246913580246,
              "top_chars": [
                [
                  "L",
                  2
                ],
                [
                  "O",
                  1
                ],
                [
                  "S",
                  1
                ]
              ]
            },
            {
              "size": 9,
              "unique": 8,
              "entropy": -0.13580246913580246,
              "top_chars": [
                [
                  "B",
                  2
                ],
                [
                  "R",
                  1
                ],
                [
                  "O",
                  1
                ]
              ]
            },
            {
              "size": 9,
              "unique": 7,
              "entropy": -0.16049382716049382,
              "top_chars": [
                [
                  "T",
                  2
                ],
                [
                  "A",
                  2
                ],
                [
                  "K",
                  1
                ]
              ]
            },
            {
              "size": 9,
              "unique": 8,
              "entropy": -0.13580246913580246,
              "top_chars": [
                [
                  "W",
                  2
                ],
                [
                  "R",
                  1
                ],
                [
                  "O",
                  1
                ]
              ]
            },
            {
              "size": 9,
              "unique": 9,
              "entropy": -0.1111111111111111,
              "top_chars": [
                [
                  "U",
                  1
                ],
                [
                  "L",
                  1
                ],
                [
                  "Q",
                  1
                ]
              ]
            },
            {
              "size": 9,
              "unique": 9,
              "entropy": -0.1111111111111111,
              "top_chars": [
                [
                  "O",
                  1
                ],
                [
                  "I",
                  1
                ],
                [
                  "P",
                  1
                ]
              ]
            },
            {
              "size": 9,
              "unique": 8,
              "entropy": -0.13580246913580246,
              "top_chars": [
                [
                  "F",
                  2
                ],
                [
                  "X",
                  1
                ],
                [
                  "R",
                  1
                ]
              ]
            },
            {
              "size": 9,
              "unique": 7,
              "entropy": -0.16049382716049382,
              "top_chars": [
                [
                  "B",
                  2
                ],
                [
                  "J",
                  2
                ],
                [
                  "O",
                  1
                ]
              ]
            },
            {
              "size": 9,
              "unique": 7,
              "entropy": -0.18518518518518517,
              "top_chars": [
                [
                  "G",
                  3
                ],
                [
                  "B",
                  1
                ],
                [
                  "Q",
                  1
                ]
              ]
            },
            {
              "size": 8,
              "unique": 7,
              "entropy": -0.15625,
              "top_chars": [
                [
                  "K",
                  2
                ],
                [
                  "H",
                  1
                ],
                [
                  "W",
                  1
                ]
              ]
            },
            {
              "size": 8,
              "unique": 5,
              "entropy": -0.25,
              "top_chars": [
                [
                  "U",
                  3
                ],
                [
                  "S",
                  2
                ],
                [
                  "F",
                  1
                ]
              ]
            }
          ]
        },
        "12": {
          "variance": 0.0007017342637973333,
          "mean_entropy": -0.14412937242798354,
          "groups": [
            {
              "size": 9,
              "unique": 8,
              "entropy": -0.13580246913580246,
              "top_chars": [
                [
                  "W",
                  2
                ],
                [
                  "O",
                  1
                ],
                [
                  "B",
                  1
                ]
              ]
            },
            {
              "size": 8,
              "unique": 8,
              "entropy": -0.125,
              "top_chars": [
                [
                  "B",
                  1
                ],
                [
                  "S",
                  1
                ],
                [
                  "Q",
                  1
                ]
              ]
            },
            {
              "size": 8,
              "unique": 6,
              "entropy": -0.1875,
              "top_chars": [
                [
                  "K",
                  2
                ],
                [
                  "Q",
                  2
                ],
                [
                  "O",
                  1
                ]
              ]
            },
            {
              "size": 8,
              "unique": 8,
              "entropy": -0.125,
              "top_chars": [
                [
                  "R",
                  1
                ],
                [
                  "L",
                  1
                ],
                [
                  "P",
                  1
                ]
              ]
            },
            {
              "size": 8,
              "unique": 8,
              "entropy": -0.125,
              "top_chars": [
                [
                  "U",
                  1
                ],
                [
                  "I",
                  1
                ],
                [
                  "R",
                  1
                ]
              ]
            },
            {
              "size": 8,
              "unique": 8,
              "entropy": -0.125,
              "top_chars": [
                [
                  "O",
                  1
                ],
                [
                  "F",
                  1
                ],
                [
                  "N",
                  1
                ]
              ]
            },
            {
              "size": 8,
              "unique": 8,
              "entropy": -0.125,
              "top_chars": [
                [
                  "X",
                  1
                ],
                [
                  "B",
                  1
                ],
                [
                  "G",
                  1
                ]
              ]
            },
            {
              "size": 8,
              "unique": 8,
              "entropy": -0.125,
              "top_chars": [
                [
                  "O",
                  1
                ],
                [
                  "B",
                  1
                ],
                [
                  "K",
                  1
                ]
              ]
            },
            {
              "size": 8,
              "unique": 6,
              "entropy": -0.1875,
              "top_chars": [
                [
                  "E",
                  2
                ],
                [
                  "T",
                  2
                ],
                [
                  "G",
                  1
                ]
              ]
            },
            {
              "size": 8,
              "unique": 7,
              "entropy": -0.15625,
              "top_chars": [
                [
                  "K",
                  2
                ],
                [
                  "H",
                  1
                ],
                [
                  "F",
                  1
                ]
              ]
            },
            {
              "size": 8,
              "unique": 6,
              "entropy": -0.1875,
              "top_chars": [
                [
                  "Z",
                  2
                ],
                [
                  "C",
                  2
                ],
                [
                  "U",
                  1
                ]
              ]
            },
            {
              "size": 8,
              "unique": 8,
              "entropy": -0.125,
              "top_chars": [
                [
                  "L",
                  1
                ],
                [
                  "R",
                  1
                ],
                [
                  "T",
                  1
                ]
              ]
            }
          ]
        }
      }
    },
    "diagonals": {
      "(1, 1)": {
        "diagonal_count": 20,
        "analysis": [
          {
            "length": 7,
            "unique": 6,
            "pattern": "OLGKNGA"
          },
          {
            "length": 7,
            "unique": 7,
            "pattern": "BIKZFDU"
          },
          {
            "length": 7,
            "unique": 6,
            "pattern": "KFSZBKE"
          },
          {
            "length": 7,
            "unique": 7,
            "pattern": "RBSWNZK"
          },
          {
            "length": 7,
            "unique": 7,
            "pattern": "UBOAYXC"
          }
        ]
      },
      "(1, 2)": {
        "diagonal_count": 20,
        "analysis": [
          {
            "length": 7,
            "unique": 7,
            "pattern": "OISWYTR"
          },
          {
            "length": 6,
            "unique": 6,
            "pattern": "BFSAPJ"
          },
          {
            "length": 6,
            "unique": 6,
            "pattern": "KBOTVC"
          },
          {
            "length": 6,
            "unique": 5,
            "pattern": "RBTJTD"
          },
          {
            "length": 5,
            "unique": 4,
            "pattern": "UWWKT"
          }
        ]
      },
      "(2, 1)": {
        "diagonal_count": 20,
        "analysis": [
          {
            "length": 4,
            "unique": 4,
            "pattern": "ONWU"
          },
          {
            "length": 4,
            "unique": 4,
            "pattern": "BGIH"
          },
          {
            "length": 4,
            "unique": 3,
            "pattern": "KKNU"
          },
          {
            "length": 4,
            "unique": 4,
            "pattern": "RSFA"
          },
          {
            "length": 4,
            "unique": 3,
            "pattern": "USBU"
          }
        ]
      },
      "(1, -1)": {
        "diagonal_count": 19,
        "analysis": [
          {
            "length": 1,
            "unique": 1,
            "pattern": "O"
          },
          {
            "length": 2,
            "unique": 2,
            "pattern": "BO"
          },
          {
            "length": 3,
            "unique": 3,
            "pattern": "KLR"
          },
          {
            "length": 4,
            "unique": 4,
            "pattern": "RINS"
          },
          {
            "length": 5,
            "unique": 5,
            "pattern": "UFGSI"
          }
        ]
      }
    },
    "berlinclock": {
      "extracted": "YPVTTMZFPK",
      "target": "BERLINCLOCK",
      "patterns": []
    },
    "zones": {
      "head": {
        "length": 21,
        "periodicity": {
          "2": {
            "variance": 9.510279352503298e-05,
            "mean_entropy": -0.15024793388429755,
            "groups": [
              {
                "size": 11,
                "unique": 8,
                "entropy": -0.14049586776859505,
                "top_chars": [
                  [
                    "O",
                    2
                  ],
                  [
                    "U",
                    2
                  ],
                  [
                    "B",
                    2
                  ]
                ]
              },
              {
                "size": 10,
                "unique": 7,
                "entropy": -0.16000000000000006,
                "top_chars": [
                  [
                    "B",
                    2
                  ],
                  [
                    "O",
                    2
                  ],
                  [
                    "L",
                    2
                  ]
                ]
              }
            ]
          },
          "3": {
            "variance": 0.00037021611365634674,
            "mean_entropy": -0.19727891156462585,
            "groups": [
              {
                "size": 7,
                "unique": 6,
                "entropy": -0.18367346938775508,
                "top_chars": [
                  [
                    "B",
                    2
                  ],
                  [
                    "O",
                    1
                  ],
                  [
                    "R",
                    1
                  ]
                ]
              },
              {
                "size": 7,
                "unique": 5,
                "entropy": -0.22448979591836732,
                "top_chars": [
                  [
                    "B",
                    2
                  ],
                  [
                    "U",
                    2
                  ],
                  [
                    "O",
                    1
                  ]
                ]
              },
              {
                "size": 7,
                "unique": 6,
                "entropy": -0.18367346938775508,
                "top_chars": [
                  [
                    "O",
                    2
                  ],
                  [
                    "K",
                    1
                  ],
                  [
                    "G",
                    1
                  ]
                ]
              }
            ]
          },
          "4": {
            "variance": 0.0017416666666666665,
            "mean_entropy": -0.2116666666666667,
            "groups": [
              {
                "size": 6,
                "unique": 6,
                "entropy": -0.16666666666666669,
                "top_chars": [
                  [
                    "O",
                    1
                  ],
                  [
                    "U",
                    1
                  ],
                  [
                    "G",
                    1
                  ]
                ]
              },
              {
                "size": 5,
                "unique": 5,
                "entropy": -0.20000000000000004,
                "top_chars": [
                  [
                    "B",
                    1
                  ],
                  [
                    "O",
                    1
                  ],
                  [
                    "H",
                    1
                  ]
                ]
              },
              {
                "size": 5,
                "unique": 5,
                "entropy": -0.20000000000000004,
                "top_chars": [
                  [
                    "K",
                    1
                  ],
                  [
                    "X",
                    1
                  ],
                  [
                    "U",
                    1
                  ]
                ]
              },
              {
                "size": 5,
                "unique": 4,
                "entropy": -0.28,
                "top_chars": [
                  [
                    "L",
                    2
                  ],
                  [
                    "R",
                    1
                  ],
                  [
                    "O",
                    1
                  ]
                ]
              }
            ]
          },
          "5": {
            "variance": 0.0001440000000000002,
            "mean_entropy": -0.256,
            "groups": [
              {
                "size": 5,
                "unique": 4,
                "entropy": -0.28,
                "top_chars": [
                  [
                    "O",
                    2
                  ],
                  [
                    "U",
                    1
                  ],
                  [
                    "L",
                    1
                  ]
                ]
              },
              {
                "size": 4,
                "unique": 4,
                "entropy": -0.25,
                "top_chars": [
                  [
                    "B",
                    1
                  ],
                  [
                    "X",
                    1
                  ],
                  [
                    "L",
                    1
                  ]
                ]
              },
              {
                "size": 4,
                "unique": 4,
                "entropy": -0.25,
                "top_chars": [
                  [
                    "K",
                    1
                  ],
                  [
                    "O",
                    1
                  ],
                  [
                    "B",
                    1
                  ]
                ]
              },
              {
                "size": 4,
                "unique": 4,
                "entropy": -0.25,
                "top_chars": [
                  [
                    "R",
                    1
                  ],
                  [
                    "G",
                    1
                  ],
                  [
                    "S",
                    1
                  ]
                ]
              },
              {
                "size": 4,
                "unique": 4,
                "entropy": -0.25,
                "top_chars": [
                  [
                    "U",
                    1
                  ],
                  [
                    "H",
                    1
                  ],
                  [
                    "O",
                    1
                  ]
                ]
              }
            ]
          },
          "6": {
            "variance": 0.008594821673525379,
            "mean_entropy": -0.3703703703703704,
            "groups": [
              {
                "size": 4,
                "unique": 3,
                "entropy": -0.375,
                "top_chars": [
                  [
                    "B",
                    2
                  ],
                  [
                    "O",
                    1
                  ],
                  [
                    "X",
                    1
                  ]
                ]
              },
              {
                "size": 4,
                "unique": 3,
                "entropy": -0.375,
                "top_chars": [
                  [
                    "B",
                    2
                  ],
                  [
                    "O",
                    1
                  ],
                  [
                    "S",
                    1
                  ]
                ]
              },
              {
                "size": 4,
                "unique": 4,
                "entropy": -0.25,
                "top_chars": [
                  [
                    "K",
                    1
                  ],
                  [
                    "G",
                    1
                  ],
                  [
                    "O",
                    1
                  ]
                ]
              },
              {
                "size": 3,
                "unique": 3,
                "entropy": -0.3333333333333333,
                "top_chars": [
                  [
                    "R",
                    1
                  ],
                  [
                    "H",
                    1
                  ],
                  [
                    "L",
                    1
                  ]
                ]
              },
              {
                "size": 3,
                "unique": 2,
                "entropy": -0.5555555555555556,
                "top_chars": [
                  [
                    "U",
                    2
                  ],
                  [
                    "I",
                    1
                  ]
                ]
              },
              {
                "size": 3,
                "unique": 3,
                "entropy": -0.3333333333333333,
                "top_chars": [
                  [
                    "O",
                    1
                  ],
                  [
                    "L",
                    1
                  ],
                  [
                    "F",
                    1
                  ]
                ]
              }
            ]
          }
        }
      },
      "mid": {
        "length": 29,
        "periodicity": {
          "2": {
            "variance": 1.8955065019204953e-05,
            "mean_entropy": -0.097687074829932,
            "groups": [
              {
                "size": 15,
                "unique": 13,
                "entropy": -0.09333333333333335,
                "top_chars": [
                  [
                    "W",
                    3
                  ],
                  [
                    "O",
                    1
                  ],
                  [
                    "Q",
                    1
                  ]
                ]
              },
              {
                "size": 14,
                "unique": 11,
                "entropy": -0.10204081632653063,
                "top_chars": [
                  [
                    "T",
                    2
                  ],
                  [
                    "S",
                    2
                  ],
                  [
                    "A",
                    2
                  ]
                ]
              }
            ]
          },
          "3": {
            "variance": 0.0008066385544209044,
            "mean_entropy": -0.14016460905349798,
            "groups": [
              {
                "size": 10,
                "unique": 10,
                "entropy": -0.10000000000000003,
                "top_chars": [
                  [
                    "O",
                    1
                  ],
                  [
                    "T",
                    1
                  ],
                  [
                    "J",
                    1
                  ]
                ]
              },
              {
                "size": 10,
                "unique": 7,
                "entropy": -0.16000000000000006,
                "top_chars": [
                  [
                    "T",
                    2
                  ],
                  [
                    "Q",
                    2
                  ],
                  [
                    "I",
                    2
                  ]
                ]
              },
              {
                "size": 9,
                "unique": 7,
                "entropy": -0.16049382716049382,
                "top_chars": [
                  [
                    "W",
                    2
                  ],
                  [
                    "S",
                    2
                  ],
                  [
                    "K",
                    1
                  ]
                ]
              }
            ]
          },
          "4": {
            "variance": 0.0006454830018742186,
            "mean_entropy": -0.1690051020408163,
            "groups": [
              {
                "size": 8,
                "unique": 8,
                "entropy": -0.125,
                "top_chars": [
                  [
                    "O",
                    1
                  ],
                  [
                    "Q",
                    1
                  ],
                  [
                    "S",
                    1
                  ]
                ]
              },
              {
                "size": 7,
                "unique": 6,
                "entropy": -0.18367346938775508,
                "top_chars": [
                  [
                    "S",
                    2
                  ],
                  [
                    "T",
                    1
                  ],
                  [
                    "Z",
                    1
                  ]
                ]
              },
              {
                "size": 7,
                "unique": 6,
                "entropy": -0.18367346938775508,
                "top_chars": [
                  [
                    "W",
                    2
                  ],
                  [
                    "J",
                    1
                  ],
                  [
                    "E",
                    1
                  ]
                ]
              },
              {
                "size": 7,
                "unique": 6,
                "entropy": -0.18367346938775508,
                "top_chars": [
                  [
                    "A",
                    2
                  ],
                  [
                    "T",
                    1
                  ],
                  [
                    "Q",
                    1
                  ]
                ]
              }
            ]
          },
          "5": {
            "variance": 0.002045234567901235,
            "mean_entropy": -0.20044444444444448,
            "groups": [
              {
                "size": 6,
                "unique": 6,
                "entropy": -0.16666666666666669,
                "top_chars": [
                  [
                    "O",
                    1
                  ],
                  [
                    "S",
                    1
                  ],
                  [
                    "E",
                    1
                  ]
                ]
              },
              {
                "size": 6,
                "unique": 5,
                "entropy": -0.22222222222222227,
                "top_chars": [
                  [
                    "T",
                    2
                  ],
                  [
                    "J",
                    1
                  ],
                  [
                    "K",
                    1
                  ]
                ]
              },
              {
                "size": 6,
                "unique": 6,
                "entropy": -0.16666666666666669,
                "top_chars": [
                  [
                    "W",
                    1
                  ],
                  [
                    "Q",
                    1
                  ],
                  [
                    "Z",
                    1
                  ]
                ]
              },
              {
                "size": 6,
                "unique": 6,
                "entropy": -0.16666666666666669,
                "top_chars": [
                  [
                    "T",
                    1
                  ],
                  [
                    "S",
                    1
                  ],
                  [
                    "Z",
                    1
                  ]
                ]
              },
              {
                "size": 5,
                "unique": 4,
                "entropy": -0.28,
                "top_chars": [
                  [
                    "W",
                    2
                  ],
                  [
                    "Q",
                    1
                  ],
                  [
                    "S",
                    1
                  ]
                ]
              }
            ]
          },
          "6": {
            "variance": 0.0010138888888888882,
            "mean_entropy": -0.2216666666666667,
            "groups": [
              {
                "size": 5,
                "unique": 5,
                "entropy": -0.20000000000000004,
                "top_chars": [
                  [
                    "O",
                    1
                  ],
                  [
                    "J",
                    1
                  ],
                  [
                    "Z",
                    1
                  ]
                ]
              },
              {
                "size": 5,
                "unique": 5,
                "entropy": -0.20000000000000004,
                "top_chars": [
                  [
                    "T",
                    1
                  ],
                  [
                    "Q",
                    1
                  ],
                  [
                    "Z",
                    1
                  ]
                ]
              },
              {
                "size": 5,
                "unique": 4,
                "entropy": -0.28,
                "top_chars": [
                  [
                    "W",
                    2
                  ],
                  [
                    "S",
                    1
                  ],
                  [
                    "U",
                    1
                  ]
                ]
              },
              {
                "size": 5,
                "unique": 5,
                "entropy": -0.20000000000000004,
                "top_chars": [
                  [
                    "T",
                    1
                  ],
                  [
                    "S",
                    1
                  ],
                  [
                    "A",
                    1
                  ]
                ]
              },
              {
                "size": 5,
                "unique": 5,
                "entropy": -0.20000000000000004,
                "top_chars": [
                  [
                    "Q",
                    1
                  ],
                  [
                    "E",
                    1
                  ],
                  [
                    "T",
                    1
                  ]
                ]
              },
              {
                "size": 4,
                "unique": 4,
                "entropy": -0.25,
                "top_chars": [
                  [
                    "S",
                    1
                  ],
                  [
                    "K",
                    1
                  ],
                  [
                    "J",
                    1
                  ]
                ]
              }
            ]
          }
        }
      },
      "tail": {
        "length": 23,
        "periodicity": {
          "2": {
            "variance": 0.0014566243503993939,
            "mean_entropy": -0.13538797061524335,
            "groups": [
              {
                "size": 12,
                "unique": 11,
                "entropy": -0.09722222222222224,
                "top_chars": [
                  [
                    "C",
                    2
                  ],
                  [
                    "W",
                    1
                  ],
                  [
                    "D",
                    1
                  ]
                ]
              },
              {
                "size": 11,
                "unique": 7,
                "entropy": -0.17355371900826447,
                "top_chars": [
                  [
                    "U",
                    3
                  ],
                  [
                    "G",
                    2
                  ],
                  [
                    "K",
                    2
                  ]
                ]
              }
            ]
          },
          "3": {
            "variance": 0.000574576131472997,
            "mean_entropy": -0.15497448979591835,
            "groups": [
              {
                "size": 8,
                "unique": 7,
                "entropy": -0.15625,
                "top_chars": [
                  [
                    "K",
                    2
                  ],
                  [
                    "W",
                    1
                  ],
                  [
                    "T",
                    1
                  ]
                ]
              },
              {
                "size": 8,
                "unique": 8,
                "entropy": -0.125,
                "top_chars": [
                  [
                    "G",
                    1
                  ],
                  [
                    "Z",
                    1
                  ],
                  [
                    "J",
                    1
                  ]
                ]
              },
              {
                "size": 7,
                "unique": 6,
                "entropy": -0.18367346938775508,
                "top_chars": [
                  [
                    "C",
                    2
                  ],
                  [
                    "D",
                    1
                  ],
                  [
                    "X",
                    1
                  ]
                ]
              }
            ]
          },
          "4": {
            "variance": 0.0016058641975308643,
            "mean_entropy": -0.2227777777777778,
            "groups": [
              {
                "size": 6,
                "unique": 5,
                "entropy": -0.2222222222222222,
                "top_chars": [
                  [
                    "C",
                    2
                  ],
                  [
                    "W",
                    1
                  ],
                  [
                    "Z",
                    1
                  ]
                ]
              },
              {
                "size": 6,
                "unique": 5,
                "entropy": -0.2222222222222222,
                "top_chars": [
                  [
                    "U",
                    2
                  ],
                  [
                    "G",
                    1
                  ],
                  [
                    "X",
                    1
                  ]
                ]
              },
              {
                "size": 6,
                "unique": 6,
                "entropy": -0.16666666666666669,
                "top_chars": [
                  [
                    "D",
                    1
                  ],
                  [
                    "T",
                    1
                  ],
                  [
                    "I",
                    1
                  ]
                ]
              },
              {
                "size": 5,
                "unique": 4,
                "entropy": -0.28,
                "top_chars": [
                  [
                    "K",
                    2
                  ],
                  [
                    "J",
                    1
                  ],
                  [
                    "G",
                    1
                  ]
                ]
              }
            ]
          },
          "5": {
            "variance": 0.0034160000000000032,
            "mean_entropy": -0.25200000000000006,
            "groups": [
              {
                "size": 5,
                "unique": 5,
                "entropy": -0.20000000000000004,
                "top_chars": [
                  [
                    "W",
                    1
                  ],
                  [
                    "X",
                    1
                  ],
                  [
                    "I",
                    1
                  ]
                ]
              },
              {
                "size": 5,
                "unique": 3,
                "entropy": -0.3600000000000001,
                "top_chars": [
                  [
                    "G",
                    2
                  ],
                  [
                    "A",
                    2
                  ],
                  [
                    "T",
                    1
                  ]
                ]
              },
              {
                "size": 5,
                "unique": 5,
                "entropy": -0.20000000000000004,
                "top_chars": [
                  [
                    "D",
                    1
                  ],
                  [
                    "J",
                    1
                  ],
                  [
                    "K",
                    1
                  ]
                ]
              },
              {
                "size": 4,
                "unique": 4,
                "entropy": -0.25,
                "top_chars": [
                  [
                    "K",
                    1
                  ],
                  [
                    "C",
                    1
                  ],
                  [
                    "U",
                    1
                  ]
                ]
              },
              {
                "size": 4,
                "unique": 4,
                "entropy": -0.25,
                "top_chars": [
                  [
                    "Z",
                    1
                  ],
                  [
                    "D",
                    1
                  ],
                  [
                    "H",
                    1
                  ]
                ]
              }
            ]
          },
          "6": {
            "variance": 0.0025559413580246906,
            "mean_entropy": -0.2847222222222222,
            "groups": [
              {
                "size": 4,
                "unique": 4,
                "entropy": -0.25,
                "top_chars": [
                  [
                    "W",
                    1
                  ],
                  [
                    "T",
                    1
                  ],
                  [
                    "K",
                    1
                  ]
                ]
              },
              {
                "size": 4,
                "unique": 4,
                "entropy": -0.25,
                "top_chars": [
                  [
                    "G",
                    1
                  ],
                  [
                    "J",
                    1
                  ],
                  [
                    "U",
                    1
                  ]
                ]
              },
              {
                "size": 4,
                "unique": 3,
                "entropy": -0.375,
                "top_chars": [
                  [
                    "C",
                    2
                  ],
                  [
                    "D",
                    1
                  ],
                  [
                    "H",
                    1
                  ]
                ]
              },
              {
                "size": 4,
                "unique": 4,
                "entropy": -0.25,
                "top_chars": [
                  [
                    "K",
                    1
                  ],
                  [
                    "D",
                    1
                  ],
                  [
                    "U",
                    1
                  ]
                ]
              },
              {
                "size": 4,
                "unique": 4,
                "entropy": -0.25,
                "top_chars": [
                  [
                    "Z",
                    1
                  ],
                  [
                    "I",
                    1
                  ],
                  [
                    "A",
                    1
                  ]
                ]
              },
              {
                "size": 3,
                "unique": 3,
                "entropy": -0.3333333333333333,
                "top_chars": [
                  [
                    "X",
                    1
                  ],
                  [
                    "G",
                    1
                  ],
                  [
                    "U",
                    1
                  ]
                ]
              }
            ]
          }
        }
      }
    }
  },
  "recommendations": [
    {
      "type": "period2",
      "params": {
        "period": 2
      },
      "reason": "Low variance at period 2"
    },
    {
      "type": "period3",
      "params": {
        "period": 3
      },
      "reason": "Low variance at period 3"
    },
    {
      "type": "diag_weave",
      "params": {
        "rows": 7,
        "cols": 14,
        "step": [
          1,
          1
        ]
      },
      "reason": "Standard diagonal weave for 7x14 grid"
    }
  ]
}