{
  "recipe_id": "TRAVERSE_174_row_major_F2_dc6b327c",
  "kstream": [
    10,
    0,
    2,
    20,
    0,
    3,
    4,
    0,
    4,
    14,
    0,
    5,
    24,
    0,
    1,
    14,
    15,
    12,
    2,
    5,
    8,
    16,
    24,
    19,
    4,
    14,
    15,
    18,
    7,
    19,
    10,
    0,
    2,
    20,
    0,
    3,
    4,
    0,
    4,
    14,
    0,
    5,
    24,
    0,
    1,
    14,
    15,
    12,
    2,
    5,
    8,
    16,
    24,
    19,
    4,
    14,
    15,
    18,
    7,
    19,
    10,
    0,
    2,
    20,
    0,
    3,
    4,
    0,
    4,
    14,
    0,
    5,
    24,
    0,
    1,
    14,
    15,
    12,
    2,
    5,
    8,
    16,
    24,
    19,
    4,
    14,
    15,
    18,
    7,
    19,
    10,
    0,
    2,
    20,
    0,
    3,
    4
  ],
  "provenance": {
    "table_id": "TRAVERSE_174",
    "page": 174,
    "path": "row_major",
    "family": "F2",
    "params": {
      "sliding": true,
      "offset": 0
    }
  },
  "sample_first_20": {
    "integers": [
      10,
      0,
      2,
      20,
      0,
      3,
      4,
      0,
      4,
      14,
      0,
      5,
      24,
      0,
      1,
      14,
      15,
      12,
      2,
      5
    ],
    "letters": "KACUADEAEOAFYABOPMCF"
  }
}