{
  "recipe_id": "TRAVERSE_175_diagonal_anti_F2_78a7505a",
  "kstream": [
    7,
    10,
    9,
    14,
    10,
    20,
    17,
    6,
    12,
    10,
    1,
    17,
    0,
    2,
    5,
    20,
    2,
    15,
    8,
    11,
    2,
    4,
    3,
    12,
    17,
    8,
    24,
    14,
    4,
    10,
    0,
    4,
    17,
    24,
    5,
    7,
    8,
    13,
    14,
    8,
    6,
    5,
    17,
    11,
    0,
    0,
    8,
    0,
    7,
    10,
    9,
    14,
    10,
    20,
    17,
    6,
    12,
    10,
    1,
    17,
    0,
    2,
    5,
    20,
    2,
    15,
    8,
    11,
    2,
    4,
    3,
    12,
    17,
    8,
    24,
    14,
    4,
    10,
    0,
    4,
    17,
    24,
    5,
    7,
    8,
    13,
    14,
    8,
    6,
    5,
    17,
    11,
    0,
    0,
    8,
    0,
    7
  ],
  "provenance": {
    "table_id": "TRAVERSE_175",
    "page": 175,
    "path": "diagonal_anti",
    "family": "F2",
    "params": {
      "sliding": false,
      "offset": 0
    }
  },
  "sample_first_20": {
    "integers": [
      7,
      10,
      9,
      14,
      10,
      20,
      17,
      6,
      12,
      10,
      1,
      17,
      0,
      2,
      5,
      20,
      2,
      15,
      8,
      11
    ],
    "letters": "HKJOKURGMKBRACFUCPIL"
  }
}