{
  "mechanism": "F1-anchor-search",
  "token": "TRUE",
  "start_index": 56,
  "family_vector": "B,V,B,V,B,V",
  "L": 11,
  "phase": 0,
  "unknown_before": 73,
  "unknown_after": 51,
  "gains": 22,
  "forced_slots_added": [
    {
      "class": 2,
      "slot": 1,
      "residue": 11
    },
    {
      "class": 3,
      "slot": 2,
      "residue": 9
    },
    {
      "class": 1,
      "slot": 3,
      "residue": 2
    },
    {
      "class": 5,
      "slot": 4,
      "residue": 4
    }
  ],
  "rejected": false,
  "reject_reasons": [],
  "anchors_preserved": true,
  "sha_ct": "eea813570c7f1fd3",
  "sha_forced_wheels_before": "251908eeb871c497",
  "sha_forced_wheels_after": "7c069e66baecda07"
}