{
  "page": 149,
  "table_id": "TRAVERSE_149",
  "headers": {},
  "row_labels": [
    "28",
    "28",
    "28",
    "0",
    "1",
    "0",
    "0",
    "1",
    "2",
    "1",
    "3",
    "2",
    "4",
    "2",
    "5",
    "3",
    "6",
    "7",
    "4",
    "7",
    "10",
    "9",
    "10",
    "5",
    "11",
    "6",
    "14",
    "13",
    "14",
    "15",
    "15",
    "16",
    "20",
    "7",
    "7",
    "7",
    "3",
    "8",
    "9",
    "21",
    "22",
    "23",
    "24",
    "25",
    "26",
    "12",
    "27",
    "28",
    "29",
    "13",
    "30",
    "31",
    "32",
    "33",
    "34",
    "35",
    "36",
    "16",
    "32",
    "38",
    "39",
    "40",
    "41",
    "42",
    "43",
    "20",
    "44",
    "45",
    "21",
    "46",
    "47",
    "48",
    "49",
    "50",
    "51",
    "52",
    "24",
    "53",
    "54",
    "55",
    "56",
    "57",
    "58",
    "27",
    "59",
    "60",
    "61",
    "62",
    "63",
    "64",
    "65",
    "66",
    "67",
    "68",
    "69",
    "70",
    "0",
    "0",
    "1",
    "1",
    "2",
    "1",
    "3",
    "2",
    "4",
    "5",
    "6",
    "7",
    "7",
    "8",
    "3",
    "4",
    "4",
    "2",
    "3",
    "9",
    "10",
    "11",
    "12",
    "13",
    "14",
    "14",
    "5",
    "5",
    "6",
    "6",
    "7",
    "7",
    "8",
    "15",
    "8",
    "16",
    "17",
    "18",
    "9",
    "1938",
    "20",
    "21",
    "11",
    "22",
    "22",
    "12",
    "29",
    "24",
    "13",
    "2555",
    "14",
    "26",
    "2731",
    "28",
    "15",
    "29",
    "2995",
    "3083",
    "31",
    "32",
    "3347",
    "34",
    "18",
    "3524",
    "36",
    "37",
    "3788",
    "38",
    "3964",
    "40",
    "41",
    "42",
    "43",
    "4404",
    "44",
    "45",
    "46",
    "4757",
    "48",
    "26",
    "49",
    "50",
    "51",
    "27",
    "51",
    "52",
    "53",
    "29",
    "54",
    "29",
    "30",
    "56",
    "57",
    "30",
    "58",
    "31",
    "59",
    "32",
    "59",
    "32",
    "60",
    "33",
    "61",
    "0",
    "0",
    "0",
    "1",
    "2",
    "1",
    "3",
    "2",
    "4",
    "2",
    "5",
    "6",
    "7",
    "3",
    "791",
    "8",
    "9",
    "5",
    "9",
    "10",
    "5",
    "6",
    "11",
    "6",
    "12",
    "13",
    "7",
    "7",
    "14",
    "1494",
    "15",
    "16",
    "9",
    "17",
    "18",
    "19",
    "20",
    "21",
    "21",
    "11",
    "2285",
    "23",
    "24",
    "25",
    "26",
    "27",
    "28",
    "15",
    "29",
    "29",
    "16",
    "30",
    "31",
    "32",
    "33",
    "18",
    "34",
    "35",
    "19",
    "3603",
    "36",
    "20",
    "37",
    "21",
    "38",
    "39",
    "21",
    "40",
    "41",
    "42",
    "22",
    "43",
    "43",
    "44",
    "45",
    "46",
    "47",
    "48",
    "49",
    "50",
    "50",
    "28",
    "51",
    "52",
    "53",
    "54",
    "55",
    "56",
    "57",
    "58",
    "58",
    "59",
    "60",
    "6152",
    "3",
    "088",
    "175",
    "1",
    "2",
    "1",
    "2",
    "4",
    "5",
    "6",
    "7",
    "4",
    "7",
    "8",
    "964",
    "10",
    "11",
    "6",
    "12",
    "7",
    "13",
    "7",
    "14",
    "8",
    "14",
    "8",
    "15",
    "9",
    "16",
    "17",
    "9",
    "1844",
    "19",
    "20",
    "21",
    "21",
    "22",
    "23",
    "24",
    "25",
    "26",
    "11",
    "14",
    "27",
    "28",
    "15",
    "15",
    "28",
    "29",
    "16",
    "30",
    "31",
    "32",
    "33",
    "34",
    "3507",
    "17",
    "35",
    "19",
    "36",
    "37",
    "21",
    "38",
    "39",
    "21",
    "40",
    "41",
    "22",
    "42",
    "42",
    "43",
    "24",
    "44",
    "45",
    "46",
    "47",
    "48",
    "49",
    "27",
    "49",
    "27",
    "50",
    "28",
    "51",
    "52",
    "29",
    "53",
    "54",
    "55",
    "56",
    "56",
    "31",
    "57",
    "58",
    "59",
    "60",
    "61",
    "62",
    "61",
    "61",
    "61"
  ],
  "col_labels": [],
  "cells": [
    [
      "15"
    ],
    [
      "30"
    ],
    [
      "45"
    ],
    [
      "88"
    ],
    [
      "77"
    ],
    [
      "47"
    ],
    [
      "94"
    ],
    [
      "41"
    ],
    [
      "65"
    ],
    [
      "88"
    ],
    [
      "53"
    ],
    [
      "35"
    ],
    [
      "41"
    ],
    [
      "82"
    ],
    [
      "30"
    ],
    [
      "29"
    ],
    [
      "18"
    ],
    [
      "06",
      "376"
    ],
    [
      "23"
    ],
    [
      "95"
    ],
    [
      "883",
      "4",
      "69"
    ],
    [
      "71",
      "5",
      "16"
    ],
    [
      "60"
    ],
    [
      "63"
    ],
    [
      "48"
    ],
    [
      "10"
    ],
    [
      "12",
      "36",
      "657"
    ],
    [
      "24"
    ],
    [
      "13"
    ],
    [
      "01"
    ],
    [
      "89"
    ],
    [
      "78"
    ],
    [
      "17",
      "66"
    ],
    [
      "04"
    ],
    [
      "51"
    ],
    [
      "98"
    ],
    [
      "45"
    ],
    [
      "92"
    ],
    [
      "39"
    ],
    [
      "1854",
      "9",
      "86"
    ],
    [
      "19",
      "42",
      "10",
      "33"
    ],
    [
      "20",
      "31",
      "10",
      "80"
    ],
    [
      "21",
      "19",
      "11",
      "27"
    ],
    [
      "22",
      "07",
      "11",
      "74"
    ],
    [
      "22",
      "96"
    ],
    [
      "21"
    ],
    [
      "23",
      "84",
      "12",
      "68"
    ],
    [
      "24",
      "72",
      "13",
      "15"
    ],
    [
      "25",
      "61"
    ],
    [
      "61"
    ],
    [
      "26",
      "49",
      "14",
      "08"
    ],
    [
      "2737",
      "14",
      "55"
    ],
    [
      "28",
      "25",
      "15",
      "02"
    ],
    [
      "29",
      "14",
      "15",
      "49"
    ],
    [
      "30",
      "02",
      "15",
      "96"
    ],
    [
      "30",
      "90",
      "16",
      "43"
    ],
    [
      "31",
      "79"
    ],
    [
      "90"
    ],
    [
      "67",
      "17",
      "37"
    ],
    [
      "33",
      "55",
      "17",
      "84"
    ],
    [
      "34",
      "44",
      "18",
      "31"
    ],
    [
      "35",
      "32",
      "18",
      "78"
    ],
    [
      "36",
      "20",
      "19",
      "25"
    ],
    [
      "37",
      "08",
      "19",
      "72"
    ],
    [
      "37",
      "97",
      "20",
      "19"
    ],
    [
      "66"
    ],
    [
      "38",
      "85"
    ],
    [
      "39",
      "73"
    ],
    [
      "13"
    ],
    [
      "40",
      "62",
      "21",
      "60"
    ],
    [
      "41",
      "50",
      "22",
      "07"
    ],
    [
      "42",
      "38",
      "22",
      "53"
    ],
    [
      "43",
      "26",
      "23",
      "00"
    ],
    [
      "44",
      "15",
      "23",
      "47"
    ],
    [
      "45",
      "03",
      "23",
      "94"
    ],
    [
      "45",
      "91"
    ],
    [
      "41"
    ],
    [
      "46",
      "80",
      "24",
      "88"
    ],
    [
      "4768",
      "25",
      "35"
    ],
    [
      "48",
      "56",
      "25",
      "82"
    ],
    [
      "49",
      "45",
      "26",
      "29"
    ],
    [
      "50",
      "33",
      "26",
      "76"
    ],
    [
      "51",
      "21"
    ],
    [
      "23"
    ],
    [
      "52",
      "10",
      "27",
      "70"
    ],
    [
      "52",
      "98",
      "28",
      "17"
    ],
    [
      "53",
      "86",
      "28",
      "64"
    ],
    [
      "54",
      "74",
      "29",
      "11"
    ],
    [
      "55",
      "63",
      "29",
      "58"
    ],
    [
      "5651",
      "30",
      "04"
    ],
    [
      "57",
      "39",
      "30",
      "51"
    ],
    [
      "58",
      "28",
      "30",
      "98"
    ],
    [
      "59",
      "16",
      "31",
      "45"
    ],
    [
      "6004",
      "31",
      "92"
    ],
    [
      "60",
      "92",
      "32",
      "39"
    ],
    [
      "6181",
      "32",
      "86"
    ],
    [
      "88",
      "0",
      "47"
    ],
    [
      "95"
    ],
    [
      "76"
    ],
    [
      "42"
    ],
    [
      "64"
    ],
    [
      "89"
    ],
    [
      "52"
    ],
    [
      "37"
    ],
    [
      "40"
    ],
    [
      "29"
    ],
    [
      "17"
    ],
    [
      "05"
    ],
    [
      "93"
    ],
    [
      "81"
    ],
    [
      "79"
    ],
    [
      "26"
    ],
    [
      "73"
    ],
    [
      "84"
    ],
    [
      "31"
    ],
    [
      "69"
    ],
    [
      "57"
    ],
    [
      "45"
    ],
    [
      "33"
    ],
    [
      "21"
    ],
    [
      "09"
    ],
    [
      "98"
    ],
    [
      "21"
    ],
    [
      "68"
    ],
    [
      "15"
    ],
    [
      "63"
    ],
    [
      "10"
    ],
    [
      "57"
    ],
    [
      "05"
    ],
    [
      "86",
      "8",
      "52"
    ],
    [
      "99"
    ],
    [
      "74"
    ],
    [
      "62",
      "9",
      "47"
    ],
    [
      "50"
    ],
    [
      "94"
    ],
    [
      "10",
      "41"
    ],
    [
      "26",
      "10",
      "89"
    ],
    [
      "14",
      "11",
      "36"
    ],
    [
      "83"
    ],
    [
      "02"
    ],
    [
      "90"
    ],
    [
      "31"
    ],
    [
      "78",
      "12",
      "73"
    ],
    [
      "66"
    ],
    [
      "25"
    ],
    [
      "13",
      "73"
    ],
    [
      "20"
    ],
    [
      "43"
    ],
    [
      "14",
      "67"
    ],
    [
      "19"
    ],
    [
      "15"
    ],
    [
      "07",
      "15",
      "62"
    ],
    [
      "16",
      "09"
    ],
    [
      "1657"
    ],
    [
      "71",
      "17",
      "04"
    ],
    [
      "59",
      "17",
      "51"
    ],
    [
      "17",
      "99"
    ],
    [
      "35"
    ],
    [
      "46"
    ],
    [
      "18",
      "93"
    ],
    [
      "12",
      "19",
      "41"
    ],
    [
      "00",
      "19",
      "88"
    ],
    [
      "20",
      "35"
    ],
    [
      "76",
      "20",
      "83"
    ],
    [
      "21",
      "30"
    ],
    [
      "52",
      "21",
      "77"
    ],
    [
      "40",
      "22",
      "25"
    ],
    [
      "28",
      "22",
      "72"
    ],
    [
      "16",
      "23",
      "19"
    ],
    [
      "23",
      "67"
    ],
    [
      "93",
      "24",
      "14"
    ],
    [
      "81",
      "24",
      "61"
    ],
    [
      "69",
      "25",
      "09"
    ],
    [
      "25",
      "56"
    ],
    [
      "45"
    ],
    [
      "03"
    ],
    [
      "33",
      "26",
      "50"
    ],
    [
      "21",
      "26",
      "97"
    ],
    [
      "09"
    ],
    [
      "46"
    ],
    [
      "97",
      "27",
      "92"
    ],
    [
      "85",
      "28",
      "40"
    ],
    [
      "73",
      "28",
      "87"
    ],
    [
      "85"
    ],
    [
      "62"
    ],
    [
      "82"
    ],
    [
      "29"
    ],
    [
      "38"
    ],
    [
      "26"
    ],
    [
      "76"
    ],
    [
      "14",
      "31",
      "24"
    ],
    [
      "70"
    ],
    [
      "02"
    ],
    [
      "18"
    ],
    [
      "90"
    ],
    [
      "66"
    ],
    [
      "78"
    ],
    [
      "13"
    ],
    [
      "66"
    ],
    [
      "43"
    ],
    [
      "95"
    ],
    [
      "38"
    ],
    [
      "76"
    ],
    [
      "64",
      "143"
    ],
    [
      "91"
    ],
    [
      "52"
    ],
    [
      "39"
    ],
    [
      "39"
    ],
    [
      "86"
    ],
    [
      "27"
    ],
    [
      "15",
      "334"
    ],
    [
      "03"
    ],
    [
      "82"
    ],
    [
      "429"
    ],
    [
      "79",
      "477"
    ],
    [
      "54"
    ],
    [
      "25"
    ],
    [
      "67"
    ],
    [
      "55"
    ],
    [
      "73"
    ],
    [
      "20"
    ],
    [
      "42"
    ],
    [
      "68"
    ],
    [
      "30"
    ],
    [
      "18"
    ],
    [
      "16"
    ],
    [
      "63"
    ],
    [
      "06"
    ],
    [
      "8",
      "11"
    ],
    [
      "32",
      "859"
    ],
    [
      "70"
    ],
    [
      "07"
    ],
    [
      "58"
    ],
    [
      "46",
      "10",
      "02"
    ],
    [
      "33",
      "10",
      "50"
    ],
    [
      "21",
      "10",
      "97"
    ],
    [
      "09",
      "11",
      "45"
    ],
    [
      "97"
    ],
    [
      "93"
    ],
    [
      "12",
      "41"
    ],
    [
      "73",
      "12",
      "88"
    ],
    [
      "61",
      "1336"
    ],
    [
      "49",
      "13",
      "84"
    ],
    [
      "36",
      "14",
      "31"
    ],
    [
      "24",
      "14",
      "79"
    ],
    [
      "12"
    ],
    [
      "27"
    ],
    [
      "00",
      "15",
      "75"
    ],
    [
      "88"
    ],
    [
      "22"
    ],
    [
      "76",
      "16",
      "70"
    ],
    [
      "64",
      "17",
      "18"
    ],
    [
      "52",
      "17",
      "65"
    ],
    [
      "40"
    ],
    [
      "13"
    ],
    [
      "27",
      "18",
      "61"
    ],
    [
      "15"
    ],
    [
      "09"
    ],
    [
      "19",
      "56"
    ],
    [
      "91"
    ],
    [
      "04"
    ],
    [
      "79",
      "20",
      "52"
    ],
    [
      "00"
    ],
    [
      "67"
    ],
    [
      "55"
    ],
    [
      "47"
    ],
    [
      "43",
      "21",
      "95"
    ],
    [
      "30",
      "22",
      "43"
    ],
    [
      "18"
    ],
    [
      "90"
    ],
    [
      "06",
      "23",
      "38"
    ],
    [
      "94",
      "23",
      "86"
    ],
    [
      "82",
      "24",
      "34"
    ],
    [
      "70",
      "24",
      "81"
    ],
    [
      "58",
      "25",
      "29"
    ],
    [
      "46",
      "25",
      "77"
    ],
    [
      "34",
      "26",
      "24"
    ],
    [
      "22",
      "26",
      "72"
    ],
    [
      "09",
      "27",
      "20"
    ],
    [
      "97",
      "27",
      "67"
    ],
    [
      "15"
    ],
    [
      "85"
    ],
    [
      "73",
      "28",
      "63"
    ],
    [
      "61",
      "29",
      "11"
    ],
    [
      "49",
      "29",
      "58"
    ],
    [
      "37",
      "30",
      "06"
    ],
    [
      "25",
      "30",
      "54"
    ],
    [
      "12",
      "31",
      "02"
    ],
    [
      "00",
      "31",
      "49"
    ],
    [
      "88",
      "31",
      "97"
    ],
    [
      "76",
      "32",
      "45"
    ],
    [
      "64",
      "32",
      "92"
    ],
    [
      "33",
      "40"
    ],
    [
      "51"
    ],
    [
      "048"
    ],
    [
      "0",
      "96"
    ],
    [
      "44"
    ],
    [
      "63"
    ],
    [
      "92",
      "4"
    ],
    [
      "40"
    ],
    [
      "38"
    ],
    [
      "26",
      "289"
    ],
    [
      "14",
      "337"
    ],
    [
      "01",
      "385"
    ],
    [
      "33"
    ],
    [
      "89"
    ],
    [
      "77",
      "481"
    ],
    [
      "5",
      "29"
    ],
    [
      "52",
      "577"
    ],
    [
      "40"
    ],
    [
      "25"
    ],
    [
      "27",
      "673"
    ],
    [
      "21"
    ],
    [
      "15"
    ],
    [
      "70"
    ],
    [
      "03"
    ],
    [
      "18"
    ],
    [
      "90"
    ],
    [
      "66"
    ],
    [
      "78"
    ],
    [
      "14"
    ],
    [
      "66"
    ],
    [
      "53"
    ],
    [
      "62"
    ],
    [
      "10",
      "10"
    ],
    [
      "29",
      "10",
      "58"
    ],
    [
      "16",
      "11",
      "06"
    ],
    [
      "04"
    ],
    [
      "92",
      "12",
      "02"
    ],
    [
      "79",
      "12",
      "51"
    ],
    [
      "67",
      "12",
      "99"
    ],
    [
      "55",
      "13",
      "47"
    ],
    [
      "43",
      "13",
      "95"
    ],
    [
      "30",
      "14",
      "43"
    ],
    [
      "54",
      "24"
    ],
    [
      "91"
    ],
    [
      "18"
    ],
    [
      "06"
    ],
    [
      "39"
    ],
    [
      "87"
    ],
    [
      "93"
    ],
    [
      "81"
    ],
    [
      "35"
    ],
    [
      "69",
      "16",
      "83"
    ],
    [
      "56"
    ],
    [
      "44",
      "17",
      "80"
    ],
    [
      "32",
      "18",
      "28"
    ],
    [
      "19",
      "18",
      "76"
    ],
    [
      "19",
      "24"
    ],
    [
      "32",
      "36"
    ],
    [
      "95"
    ],
    [
      "72",
      "4"
    ],
    [
      "82",
      "20",
      "20",
      "42"
    ],
    [
      "70",
      "20",
      "68"
    ],
    [
      "16",
      "44"
    ],
    [
      "58"
    ],
    [
      "45"
    ],
    [
      "64",
      "45"
    ],
    [
      "33",
      "22",
      "13"
    ],
    [
      "21"
    ],
    [
      "61"
    ],
    [
      "08",
      "23",
      "09",
      "48"
    ],
    [
      "96",
      "23",
      "57",
      "49"
    ],
    [
      "84",
      "24",
      "05",
      "50"
    ],
    [
      "53"
    ],
    [
      "71"
    ],
    [
      "50",
      "25",
      "01"
    ],
    [
      "47",
      "25",
      "49",
      "58"
    ],
    [
      "35",
      "25",
      "97",
      "54"
    ],
    [
      "22",
      "26",
      "46",
      "55"
    ],
    [
      "10",
      "26",
      "94",
      "56"
    ],
    [
      "42",
      "57"
    ],
    [
      "98"
    ],
    [
      "90",
      "58"
    ],
    [
      "85"
    ],
    [
      "38",
      "59"
    ],
    [
      "73"
    ],
    [
      "60",
      "28",
      "86"
    ],
    [
      "34"
    ],
    [
      "43"
    ],
    [
      "36",
      "29",
      "82",
      "62"
    ],
    [
      "24",
      "30",
      "30",
      "63"
    ],
    [
      "11",
      "30",
      "78"
    ],
    [
      "99"
    ],
    [
      "26",
      "65"
    ],
    [
      "87",
      "31",
      "75",
      "66"
    ],
    [
      "74",
      "32",
      "23"
    ],
    [
      "62",
      "32",
      "71"
    ],
    [
      "50",
      "33",
      "19",
      "69"
    ],
    [
      "37",
      "33",
      "67",
      "70"
    ],
    [
      "0"
    ],
    [
      "45"
    ],
    [
      "30"
    ],
    [
      "15"
    ]
  ],
  "verbatim_block": "62\nTRAVERSE TABLE .\n28 Deg.\nDist.\n28\u00b0 0\u2032\nLat. Dep.\n28\u00b0 15'\nLat Dep.\n28\u00b0 30'\nDep\nLat\n28\u00b0 45\u2032\nLat. Dep.\nDist\n1\n2\n3\n4\n5\n6\n7\n8\n9\n0.88\n1.77\n0.47\n0.94\n1.41\n2.65\n1.88\n3.53\n2.35\n4.41\n2.82\n5.30\n3.29\n6.18\n7.06 376\n4.23\n7.95\n10 883 4.69\n11\n12\n13\n9.71 5 16\n10-60\n5.63\n11.48\n6.10\n14 12.36 657\n13.24\n15\n14.13\n16\n15.01\n17\n15.89\n18\n16.78\n19\n20 17.66\n7.04\n7.51\n7.98\n3.45\n8.92\n9.39\n21 1854 9.86\n22 19.42 10.33\n23 20.31 10 80\n24 21.19 11.27\n25 22.07 11.74\n26 22.96\n12.21\n27 23.84 12.68\n28 24.72 13.15\n29 25.61\n13.61\n30 26.49 14 08\n31 2737 14 55\n32 28 25 15.02\n33 29.14 15.49\n34 30.02 15 96\n35 30 90 16.43\n36 31.79\n16 90\n32.67 17 37\n37\n38 33 55 17 84\n39 34.44 18.31\n40 35.32 18 78\n41 36 20 19.25\n42 37.08 19 72\n43 37.97 20 19\n20.66\n44 38.85\n45 39.73\n21.13\n46 40.62 21 60\n47 41.50 22.07\n48 42.38 22 53\n49 43.26 23.00\n50 44.15 23.47\n51 45.03 23 94\n52 45.91\n24.41\n53 46.80 24 88\n54 4768 25 35\n55 48.56 25 82\n56 49 45 26.29\n57 50.33 26.76\n58 51.21\n27.23\n59 52.10 27.70\n60 52.98 28.17\n61 53.86 28.64\n62 54.74 29 11\n63 55.63 29.58\n64 5651 30.04\n65 57.39 30.51\n66 58.28 30.98\n67 59.16 31 45\n68 6004 31.92\n69 60.92 32 39\n70 6181 32.86\n0.88 0.47\n0.95\n1.76\n1.42\n2.64\n1.89\n3.52\n2.37\n4.40\n5.29\n6.17\n7.05\n7.93\n8.81\n3.79\n4.26\n4.73\n2.84\n3.31\n9.69\n10.57\n11.45\n12.33\n13.21\n14.09\n14.98\n5.21\n5.68\n6.15\n6.63\n7.10\n7.57\n8.05\n15.86 8.52\n8.99\n16.74\n17.62 9.47\n18.50\n9.94\n1938 10 41\n20.26 10.89\n21 14 11.36\n11.83\n22.02\n22.90\n12 31\n:\n29.78 12.73\n24.66\n13.25\n2555 13.73\n14.20\n26.43\n2731 14.67\n28.19\n15.15\n29 07 15 62\n2995 16,09\n3083 1657\n31.71 17.04\n32.59 17.51\n3347 17 99\n34.35\n18 46\n3524 18 93\n36 12 19.41\n37.00 19.88\n3788 20.35\n38.76 20.83\n3964 21 30\n40.52 21.77\n41.40 22.25\n42 28 22 72\n43.16 23 19\n4404 23.67\n44.93 24.14\n45.81 24.61\n46.69 25.09\n4757 25.56\n48.45\n26.03\n49.33 26.50\n50.21 26 97\n51.09\n27.46\n51.97 27.92\n52.85 28.40\n53 73 28.87\n29 85\n54.62\n29.82\n5550\n30.29\n56.38\n57.26\n30.76\n58.14 31.24\n31.70\n59-02\n32.18\n59.90\n32.66\n60.78\n33.13\n61.66\n0.43\n0.95\n0.38\n1.76\n2.64 143\n1.91\n3.52\n2.39\n4.39\n2.86\n5.27\n6.15 334\n7.03\n3.82\n791 429\n8.79 477\n9"
}